{
  "url": "https://fahrplan.events.ccc.de/congress/2019/Lineup/events/11308.html",
  "id": 11308,
  "guid": "0195c187-3c0a-44e1-86a7-aa29fe326b5d",
  "logo": null,
  "date": "2019-12-27T22:00:00+01:00",
  "start": "22:00",
  "duration": "02:00",
  "room": "Uptown",
  "slug": "36c3-abfahrplan-11308-joghurt_bambaata",
  "title": "Joghurt Bambaata",
  "subtitle": "",
  "track": "Music",
  "type": "djset",
  "language": "en",
  "abstract": "Unter gewaltigen Opfern, schreibt er eine Reihe von Geschichten mit Ortsnamen, Jahreszahlen und sonstigen Daten, die sich durchaus belegen lassen und in ihrer Wirklichkeit nicht anzuzweifeln sind. Diese Eckdaten sind nur Bruchst\u00fccke, die aus einer Summe von Erinnerungen zusammengesetzt wurden. Das tats\u00e4chlich gelebte und dies was wir zu erleben glaubten, ist ein Teil seiner Biographie, die lediglich eine nachtr\u00e4gliche Interpretation darstellt.",
  "description": "",
  "recording_license": "",
  "do_not_record": false,
  "persons": [],
  "links": [
    {
      "url": "https://www.mixcloud.com/bambaata/",
      "title": "Mixcloud"
    },
    {
      "url": "https://audioasyl.net/artist_artist.php?artist_id=250",
      "title": "Audioasyl"
    },
    {
      "url": "https://mp25.bandcamp.com/",
      "title": "Bandcamp"
    }
  ],
  "attachments": []
}