{
  "id": 1341,
  "guid": "15b950d6-8f16-46f0-8453-c08d8d7668d3",
  "url": "https://events.ccc.de/congress/2019/wiki/index.php/Session:Junghaecksentag",
  "logo": null,
  "date": "2019-12-28T13:30:00+01:00",
  "start": "13:30",
  "duration": "1:30",
  "room": "Assembly:Haecksen",
  "slug": "36c3-1341-session_junghaecksentag",
  "title": "Junghaecksentag",
  "subtitle": "",
  "track": "self organized sessions",
  "type": "discussion",
  "language": "de",
  "abstract": "",
  "description": "Sch\u00fclerinnen fragen Haecksen\nSch\u00fclerinnen kommen uns besuchen und k\u00f6nnen uns Fragen stellen.",
  "persons": [
    {
      "id": 0,
      "url": "https://events.ccc.de/congress/2019/wiki/index.php/User:Zitro",
      "public_name": "Zitro"
    }
  ],
  "links": [
    "http://haecksen.org"
  ]
}