{
  "id": 1628,
  "guid": "289a5af8-9088-472c-969e-f460a85ddf76",
  "url": "https://events.ccc.de/congress/2019/wiki/index.php/Session:Hacking_BCI",
  "logo": null,
  "date": "2019-12-29T16:00:00+01:00",
  "start": "16:00",
  "duration": "2:20",
  "room": "Assembly:Hardware Hacking Area",
  "slug": "36c3-1628-session_hacking_bci",
  "title": "Hacking BCI",
  "subtitle": "",
  "track": "self organized sessions",
  "type": "hands-on",
  "language": "en",
  "abstract": "",
  "description": "Let us gather and to do some BCI hacking\nBring some RasperryPis, LEDs and plug your brain into our biosensing devices to make some magic happen",
  "persons": [
    {
      "id": 0,
      "url": "https://events.ccc.de/congress/2019/wiki/index.php/User:WasabiWasabi",
      "public_name": "WasabiWasabi"
    }
  ],
  "links": []
}