{
  "id": 1307,
  "guid": "38d088f0-032d-408a-b3a1-6184b7ba326d",
  "url": "https://events.ccc.de/congress/2019/wiki/index.php/Session:Borgbackup",
  "logo": null,
  "date": "2019-12-27T22:30:00+01:00",
  "start": "22:30",
  "duration": "1:30",
  "room": "Lecture room 11",
  "slug": "36c3-1307-session_borgbackup",
  "title": "Borgbackup",
  "subtitle": "",
  "track": "self organized sessions",
  "type": "discussion",
  "language": "de",
  "abstract": "",
  "description": "BorgBackup: Meeting and Q&A session\nBorgBackup user and developer meeting.Q&A, feedback, exchange experiences and tips, etc.Also we might have BorgBackup stickers for you to spread - finally!",
  "persons": [
    {
      "id": 0,
      "url": "https://events.ccc.de/congress/2019/wiki/index.php/User:TW",
      "public_name": "TW"
    }
  ],
  "links": [
    "https://www.borgbackup.org/"
  ]
}