{
  "url": "https://frab.riat.at/en/36C3/public/schedule/events/143.html",
  "id": 4343,
  "guid": "54ace740-aed5-4990-ae1e-9d1a8d274d2f",
  "logo": null,
  "date": "2019-12-28T13:15:00+01:00",
  "start": "13:15",
  "duration": "00:15",
  "room": "CDC - Stage",
  "slug": "36C3-143-funding_models_of_foss",
  "title": "Funding models of FOSS",
  "subtitle": "",
  "track": "Stage",
  "type": "lightning_talk",
  "language": "en",
  "abstract": "Diego talks about various FOSS funding models, which are the most successful, and how to make FOSS sustainable for the upcoming years.",
  "description": "FOSS is in a very strange place where the entire internet runs off of its infrastructure, but it generates little money for the people responsible for maintenance and upkeep.\r\n\r\nThis talk looks at FOSS projects, big and small, as well as the unique challenges they face to keep their developers working on them, the consequences if they fall into disrepair, and sustainable, profitable funding models for them.",
  "recording_license": "",
  "do_not_record": false,
  "persons": [
    {
      "id": 66,
      "public_name": "Diego \"rehrar\" Salazar"
    }
  ],
  "links": [],
  "attachments": [
    {
      "url": "/system/event_attachments/attachments/000/000/059/original/Funding_Models_of_FOSS.odp?1577527549",
      "title": "Funding Models of FOSS"
    },
    {
      "url": "/attachments/original/missing.png",
      "title": "file"
    }
  ]
}