{
  "id": 1234,
  "guid": "5d4714ef-b83c-4cca-9d78-c43b15114af7",
  "url": "https://events.ccc.de/congress/2019/wiki/index.php/Session:Kefir_Making",
  "logo": null,
  "date": "2019-12-28T14:00:00+01:00",
  "start": "14:00",
  "duration": "2:00",
  "room": "Assembly:Foodhackingbase",
  "slug": "36c3-1234-session_kefir_making",
  "title": "Kefir Making",
  "subtitle": "",
  "track": "self organized sessions",
  "type": "hands-on",
  "language": "en",
  "abstract": "",
  "description": "At this workshop you will learn how to make your own kefir ferments using the kefir grain culture.\nFor more information please refer to the foodhackingbase wiki page: https://foodhackingbase.org/wiki/Kefir_making_36c3",
  "persons": [
    {
      "id": 0,
      "url": "https://events.ccc.de/congress/2019/wiki/index.php/User:0x378",
      "public_name": "0x378"
    }
  ],
  "links": [
    "https://foodhackingbase.org/wiki/Kefir_making_36c3"
  ]
}