{
  "url": "https://frab.riat.at/en/36C3/public/schedule/events/175.html",
  "id": 4375,
  "guid": "b231c6ce-1717-47b7-aa0c-bba9320a510d",
  "logo": null,
  "date": "2019-12-27T17:15:00+01:00",
  "start": "17:15",
  "duration": "00:15",
  "room": "CDC - Stage",
  "slug": "36C3-175-introduction_to_monero_at_36c3",
  "title": "Introduction to Monero at 36C3",
  "subtitle": "",
  "track": "Stage",
  "type": "lightning_talk",
  "language": "en",
  "abstract": "",
  "description": "",
  "recording_license": "",
  "do_not_record": false,
  "persons": [],
  "links": [],
  "attachments": []
}