{
  "id": 836,
  "guid": "bbb85436-a57a-504e-8f90-6a45188e0fa3",
  "logo": "/media/36c3/images/3PCCCZ/chaos_ballett_promo_imgsize_M.jpg",
  "date": "2019-12-27T23:00:00+01:00",
  "start": "23:00",
  "duration": "01:00",
  "room": "cinopolis",
  "slug": "3PCCCZ",
  "url": "https://talks.komona.org/36c3/talk/3PCCCZ/",
  "title": "Chaos Ballett Screening",
  "subtitle": "",
  "track": null,
  "type": "Session",
  "language": "en",
  "abstract": "come and see, we might show you some snippets or the whole chaos ballett which took place here:\r\n\r\nhttps://www.hkw.de/en/programm/projekte/veranstaltung/p_163517.php",
  "description": "#chaosballettscreening",
  "recording_license": "",
  "do_not_record": false,
  "persons": [
    {
      "id": 28,
      "code": "3KGZHF",
      "public_name": "Chaos Ensemble",
      "biography": null,
      "answers": []
    }
  ],
  "links": [],
  "attachments": [],
  "answers": []
}