{
  "id": 1403,
  "guid": "f906f1b5-5fe4-4abd-95d3-c1d0210c4b88",
  "url": "https://events.ccc.de/congress/2019/wiki/index.php/Session:SEXUAL_HACKING:_Welcome_to_tantra_yoga",
  "logo": null,
  "date": "2019-12-29T11:00:00+01:00",
  "start": "11:00",
  "duration": "2:00",
  "room": "Hackers Beauty Palace",
  "slug": "36c3-1403-session_sexual_hacking_welcome_to_tantra_yoga",
  "title": "SEXUAL HACKING: Welcome to tantra yoga",
  "subtitle": "",
  "track": "self organized sessions",
  "type": "",
  "language": "en",
  "abstract": "",
  "description": "When is your time to breathe? Inhale. What makes you breathless? Exhale. Stop. Inhale. More. And more. What do you feel? Let go. Overcome your limits. Breathe.\n",
  "persons": [
    {
      "id": 0,
      "url": "https://events.ccc.de/congress/2019/wiki/index.php/User:Alibi",
      "public_name": "Alibi"
    }
  ],
  "links": []
}